mhi.py
easy_mhi-1.3.dist-info/LICENCE.txt
easy_mhi-1.3.dist-info/METADATA
easy_mhi-1.3.dist-info/WHEEL
easy_mhi-1.3.dist-info/top_level.txt
easy_mhi-1.3.dist-info/RECORD
