Metadata-Version: 2.1
Name: easy-mhi
Version: 1.3
Summary: Simple library that can be used to generate motion history images from video frames
Home-page: https://github.com/larrett/mhi
License: UNKNOWN
Project-URL: Bug Reports, https://github.com/larrett/mhi/issues
Platform: UNKNOWN
Classifier: Development Status :: 3 - Alpha
Classifier: Intended Audience :: Developers
Classifier: Topic :: Software Development :: Build Tools
Classifier: License :: OSI Approved :: MIT License
Classifier: Programming Language :: Python :: 3.7
Classifier: Programming Language :: Python :: 3.8
Requires-Dist: Pillow (~=8.0)
